examples/verilog_designs/generated_risc_8bit/risc_8bit_defines.vh
// Shared parameters and opcodes for the 8-bit RISC processor

//================================================================
// Parameters
//================================================================
`define D_WIDTH        8
`define A_WIDTH        8
`define REG_ADDR_WIDTH 4
`define REG_COUNT      (1 << `REG_ADDR_WIDTH)
`define IMEM_SIZE      256
`define DMEM_SIZE      256

// Instruction Opcodes
`define OP_NOP  4'h0 // No Operation
`define OP_ADD  4'h1 // Add
`define OP_SUB  4'h2 // Subtract
`define OP_AND  4'h3 // Bitwise AND
`define OP_OR   4'h4 // Bitwise OR
`define OP_SL   4'h5 // Shift Left by 1
`define OP_LW   4'h6 // Load Word
`define OP_SW   4'h7 // Store Word
`define OP_ADDI 4'h8 // Add Immediate
`define OP_JMP  4'h9 // Jump (not implemented in pipeline)
`define OP_BEQ  4'hA // Branch if Equal
`define OP_HALT 4'hF // Halt Processor

examples/verilog_designs/generated_risc_8bit/risc_8bit_processor.v
/*
 * Verilog code for a simple 8-bit, 5-stage pipelined RISC processor.
 *
 * This monolithic module defines a complete processor including:
 * - A simple 16-bit instruction set architecture (ISA).
 * - 5-stage pipeline: Fetch, Decode, Execute, Memory, Write-back.
 * - Internal instruction and data memories, pre-loaded with a test program.
 * - 16 general-purpose 8-bit registers.
 * - Hazard detection unit for load-use stalls.
 * - Forwarding unit to mitigate data hazards.
 * - Branch prediction (branch not taken) with pipeline flushing on taken branches.
 */
module risc_8bit_processor (
    input wire clk,
    input wire rst
);

    // --- Architectural Parameters (previously in risc_8bit_defines.vh) ---
    parameter D_WIDTH = 8;         // Data Width
    parameter A_WIDTH = 8;         // Address Width (for PC and Data Memory)
    parameter REG_COUNT = 16;      // Number of Registers
    parameter REG_ADDR_WIDTH = 4;  // Bits to address a register
    parameter IMEM_SIZE = 256;     // Instruction Memory Size
    parameter DMEM_SIZE = 256;     // Data Memory Size

    // --- Instruction Opcodes (previously in risc_8bit_defines.vh) ---
    localparam OP_NOP  = 4'h0;
    localparam OP_ADDI = 4'h1;
    localparam OP_ADD  = 4'h2;
    localparam OP_SW   = 4'h3;
    localparam OP_LW   = 4'h4;
    localparam OP_SUB  = 4'h5;
    localparam OP_BEQ  = 4'h6;
    localparam OP_AND  = 4'h7;
    localparam OP_OR   = 4'h8;
    localparam OP_SL   = 4'h9;
    localparam OP_HALT = 4'hF;

    //================================================================
    // Memories and Register File
    //================================================================
    reg [A_WIDTH-1:0] pc;
    reg [15:0]        instr_mem [0:IMEM_SIZE-1];
    reg [D_WIDTH-1:0] data_mem [0:DMEM_SIZE-1];
    reg [D_WIDTH-1:0] reg_file [0:REG_COUNT-1];
    reg               halted;

    //================================================================
    // Pipeline Wires and Registers
    //================================================================

    // --- IF Stage ---
    wire [15:0]       if_instr;
    wire [A_WIDTH-1:0] pc_next;
    wire [A_WIDTH-1:0] pc_plus_1;

    // --- IF/ID Pipeline Register ---
    reg [15:0]        if_id_instr;
    reg [A_WIDTH-1:0] if_id_pc_plus_1;
    reg               if_id_valid;

    // --- ID Stage ---
    wire [3:0]                 id_opcode;
    wire [REG_ADDR_WIDTH-1:0]  id_rs1_addr, id_rs2_addr, id_rd_addr;
    wire [D_WIDTH-1:0]         id_rs1_data, id_rs2_data;
    wire [3:0]                 id_imm;
    // Control Signals
    wire                       id_reg_write;
    wire [2:0]                 id_alu_op;
    wire                       id_alu_src; // 0 for reg, 1 for imm
    wire                       id_mem_read;
    wire                       id_mem_write;
    wire                       id_mem_to_reg;
    wire                       id_branch;

    // --- ID/EX Pipeline Register ---
    reg                        id_ex_reg_write;
    reg [2:0]                  id_ex_alu_op;
    reg                        id_ex_alu_src;
    reg                        id_ex_mem_read;
    reg                        id_ex_mem_write;
    reg                        id_ex_mem_to_reg;
    reg                        id_ex_branch;
    reg [A_WIDTH-1:0]          id_ex_pc_plus_1;
    reg [D_WIDTH-1:0]          id_ex_rs1_data;
    reg [D_WIDTH-1:0]          id_ex_rs2_data;
    reg [3:0]                  id_ex_imm;
    reg [REG_ADDR_WIDTH-1:0]   id_ex_rs1_addr, id_ex_rs2_addr, id_ex_rd_addr;

    // --- EX Stage ---
    wire [D_WIDTH-1:0]         ex_alu_in1, ex_alu_in2;
    wire [D_WIDTH-1:0]         ex_alu_result;
    wire                       ex_zero_flag;
    wire [A_WIDTH-1:0]         ex_branch_addr;
    wire                       ex_branch_taken;
    wire [1:0]                 forwardA, forwardB;

    // --- EX/MEM Pipeline Register ---
    reg                        ex_mem_reg_write;
    reg                        ex_mem_mem_read;
    reg                        ex_mem_mem_write;
    reg                        ex_mem_mem_to_reg;
    reg [D_WIDTH-1:0]          ex_mem_alu_result;
    reg [D_WIDTH-1:0]          ex_mem_store_data; // Data for SW
    reg [REG_ADDR_WIDTH-1:0]   ex_mem_rd_addr;
    reg                        ex_mem_branch_taken;

    // --- MEM Stage ---
    wire [D_WIDTH-1:0]         mem_read_data;

    // --- MEM/WB Pipeline Register ---
    reg                        mem_wb_reg_write;
    reg                        mem_wb_mem_to_reg;
    reg [D_WIDTH-1:0]          mem_wb_read_data;
    reg [D_WIDTH-1:0]          mem_wb_alu_result;
    reg [REG_ADDR_WIDTH-1:0]   mem_wb_rd_addr;

    // --- WB Stage ---
    wire [D_WIDTH-1:0]         wb_write_data;

    // --- Hazard Unit Signals ---
    wire                       pc_stall;
    wire                       id_ex_bubble;
    wire                       if_id_flush;

    //================================================================
    // Memory and Register Initialization
    //================================================================
    integer i;
    initial begin
        // Load a simple test program into instruction memory
        // Program: R1=5, R2=10, R3=R1+R2, store R3 at mem[20], load it back to R5, branch, halt.
        // Instruction Format: {opcode[15:12], rd[11:8], rs1[7:4], rs2/imm[3:0]}
        for (i = 0; i < IMEM_SIZE; i = i + 1) instr_mem[i] = {OP_NOP, 12'h000};
        
        instr_mem[0] = {OP_ADDI, 4'd1, 4'd0, 4'd5};    // 0: ADDI R1, R0, 5   (R0 is always 0)
        instr_mem[1] = {OP_ADDI, 4'd2, 4'd0, 4'd10};   // 1: ADDI R2, R0, 10
        instr_mem[2] = {OP_ADD,  4'd3, 4'd1, 4'd2};    // 2: ADD R3, R1, R2
        instr_mem[3] = {OP_ADDI, 4'd4, 4'd0, 4'd12};   // 3: ADDI R4, R0, 12 (address for store, NOTE: immediate must be 4-bit)
        instr_mem[4] = {OP_SW,   4'd3, 4'd4, 4'd0};    // 4: SW R3, 0(R4)  (rs2=R3, rs1=R4)
        instr_mem[5] = {OP_LW,   4'd5, 4'd4, 4'd0};    // 5: LW R5, 0(R4)
        instr_mem[6] = {OP_SUB,  4'd6, 4'd2, 4'd1};    // 6: SUB R6, R2, R1  (R6 should be 5)
        instr_mem[7] = {OP_BEQ,  4'd1, 4'd6, 4'd2};    // 7: BEQ R1, R6, 2   (branch to instr 10)
        instr_mem[8] = {OP_NOP,  12'h000};             // 8: NOP (should be skipped)
        instr_mem[9] = {OP_NOP,  12'h000};             // 9: NOP (should be skipped)
        instr_mem[10]= {OP_HALT, 12'hFFF};             // 10: HALT

        // Initialize data memory and registers to 0
        for (i = 0; i < DMEM_SIZE; i = i + 1) data_mem[i] = 8'h00;
        for (i = 0; i < REG_COUNT; i = i + 1) reg_file[i] = 8'h00;
    end

    //================================================================
    // STAGE 1: INSTRUCTION FETCH (IF)
    //================================================================
    assign pc_plus_1 = pc + 1;
    assign if_instr = instr_mem[pc];

    assign pc_next = ex_branch_taken ? ex_branch_addr : pc_plus_1;

    always @(posedge clk or posedge rst) begin
        if (rst) begin
            pc <= 0;
            halted <= 1'b0;
        end else if (~pc_stall && ~halted) begin
            pc <= pc_next;
        end
        
        // Halt logic is latched when HALT instruction is in ID stage
        if (~rst && if_id_valid && (id_opcode == OP_HALT)) begin
            halted <= 1'b1;
        end
    end

    //================================================================
    // IF/ID PIPELINE REGISTER
    //================================================================
    always @(posedge clk or posedge rst) begin
        if (rst || if_id_flush) begin
            if_id_instr <= {OP_NOP, 12'h0};
            if_id_pc_plus_1 <= 0;
            if_id_valid <= 1'b0;
        end else if (~pc_stall) begin
            if_id_instr <= if_instr;
            if_id_pc_plus_1 <= pc_plus_1;
            if_id_valid <= ~halted;
        end
    end

    //================================================================
    // STAGE 2: INSTRUCTION DECODE (ID)
    //================================================================
    assign id_opcode   = if_id_instr[15:12];
    assign id_rd_addr  = if_id_instr[11:8];
    assign id_rs1_addr = if_id_instr[7:4];
    assign id_rs2_addr = if_id_instr[3:0];
    assign id_imm      = if_id_instr[3:0];

    // Register File Read Ports (R0 is always 0)
    assign id_rs1_data = (id_rs1_addr == 0) ? 0 : reg_file[id_rs1_addr];
    assign id_rs2_data = (id_rs2_addr == 0) ? 0 : reg_file[id_rs2_addr];

    // Control Unit Logic (combinational)
    assign id_reg_write = (id_opcode == OP_ADD || id_opcode == OP_SUB || id_opcode == OP_AND || id_opcode == OP_OR || id_opcode == OP_SL || id_opcode == OP_LW || id_opcode == OP_ADDI) && if_id_valid;
    assign id_alu_src   = (id_opcode == OP_ADDI || id_opcode == OP_LW || id_opcode == OP_SW);
    assign id_mem_to_reg= (id_opcode == OP_LW);
    assign id_mem_read  = (id_opcode == OP_LW);
    assign id_mem_write = (id_opcode == OP_SW);
    assign id_branch    = (id_opcode == OP_BEQ);

    // ALU Control
    assign id_alu_op = (id_opcode == OP_ADD || id_opcode == OP_ADDI || id_opcode == OP_LW || id_opcode == OP_SW) ? 3'b001 : // ADD
                       (id_opcode == OP_SUB || id_opcode == OP_BEQ) ? 3'b010 : // SUB
                       (id_opcode == OP_AND) ? 3'b011 : // AND
                       (id_opcode == OP_OR)  ? 3'b100 : // OR
                       (id_opcode == OP_SL)  ? 3'b101 : // SL
                       3'b000; // Default

    //================================================================
    // ID/EX PIPELINE REGISTER
    //================================================================
    always @(posedge clk or posedge rst) begin
        if (rst || id_ex_bubble) begin
            id_ex_reg_write <= 0;
            id_ex_alu_op <= 3'b000;
            id_ex_alu_src <= 0;
            id_ex_mem_read <= 0;
            id_ex_mem_write <= 0;
            id_ex_mem_to_reg <= 0;
            id_ex_branch <= 0;
            // Data path registers are not cleared to save logic, as control signals are 0
            id_ex_rd_addr <= 0; // Prevent forwarding from invalid instruction
        end else begin
            id_ex_reg_write <= id_reg_write;
            id_ex_alu_op <= id_alu_op;
            id_ex_alu_src <= id_alu_src;
            id_ex_mem_read <= id_mem_read;
            id_ex_mem_write <= id_mem_write;
            id_ex_mem_to_reg <= id_mem_to_reg;
            id_ex_branch <= id_branch;
            id_ex_pc_plus_1 <= if_id_pc_plus_1;
            id_ex_rs1_data <= id_rs1_data;
            id_ex_rs2_data <= id_rs2_data;
            id_ex_imm <= id_imm;
            id_ex_rs1_addr <= id_rs1_addr;
            id_ex_rs2_addr <= id_rs2_addr;
            id_ex_rd_addr <= id_rd_addr;
        end
    end

    //================================================================
    // STAGE 3: EXECUTE (EX)
    //================================================================

    // Forwarding MUXes for ALU inputs
    assign ex_alu_in1 = (forwardA == 2'b01) ? ex_mem_alu_result :
                        (forwardA == 2'b10) ? wb_write_data :
                        id_ex_rs1_data; // Default: 2'b00

    wire [D_WIDTH-1:0] ex_alu_in2_base = id_ex_alu_src ? {{D_WIDTH-4{id_ex_imm[3]}}, id_ex_imm} : id_ex_rs2_data; // Sign-extend immediate

    assign ex_alu_in2 = (forwardB == 2'b01) ? ex_mem_alu_result :
                        (forwardB == 2'b10) ? wb_write_data :
                        ex_alu_in2_base; // Default: 2'b00

    // ALU
    reg [D_WIDTH-1:0] ex_alu_result_comb;
    always @(*) begin
        case (id_ex_alu_op)
            3'b001: ex_alu_result_comb = ex_alu_in1 + ex_alu_in2; // ADD
            3'b010: ex_alu_result_comb = ex_alu_in1 - ex_alu_in2; // SUB
            3'b011: ex_alu_result_comb = ex_alu_in1 & ex_alu_in2; // AND
            3'b100: ex_alu_result_comb = ex_alu_in1 | ex_alu_in2; // OR
            3'b101: ex_alu_result_comb = ex_alu_in1 << 1;         // SL
            default: ex_alu_result_comb = 8'h00;
        endcase
    end
    assign ex_alu_result = ex_alu_result_comb;

    assign ex_zero_flag = (ex_alu_in1 == ex_alu_in2); // For BEQ

    // Branch logic
    assign ex_branch_addr = id_ex_pc_plus_1 + {{A_WIDTH-4{id_ex_imm[3]}}, id_ex_imm};
    assign ex_branch_taken = id_ex_branch & ex_zero_flag;

    //================================================================
    // EX/MEM PIPELINE REGISTER
    //================================================================
    always @(posedge clk or posedge rst) begin
        if (rst) begin
            ex_mem_reg_write <= 0;
            ex_mem_mem_read <= 0;
            ex_mem_mem_write <= 0;
            ex_mem_mem_to_reg <= 0;
            ex_mem_alu_result <= 0;
            ex_mem_store_data <= 0;
            ex_mem_rd_addr <= 0;
            ex_mem_branch_taken <= 0;
        end else begin
            ex_mem_reg_write <= id_ex_reg_write;
            ex_mem_mem_read <= id_ex_mem_read;
            ex_mem_mem_write <= id_ex_mem_write;
            ex_mem_mem_to_reg <= id_ex_mem_to_reg;
            ex_mem_alu_result <= ex_alu_result;
            ex_mem_store_data <= ex_alu_in2; // Forwarded value for SW
            ex_mem_rd_addr <= id_ex_rd_addr;
            ex_mem_branch_taken <= ex_branch_taken;
        end
    end

    //================================================================
    // STAGE 4: MEMORY ACCESS (MEM)
    //================================================================
    assign mem_read_data = data_mem[ex_mem_alu_result];

    // Data Memory Write Port
    always @(posedge clk) begin
        if (~rst && ex_mem_mem_write) begin
            data_mem[ex_mem_alu_result] <= ex_mem_store_data;
        end
    end

    //================================================================
    // MEM/WB PIPELINE REGISTER
    //================================================================
    always @(posedge clk or posedge rst) begin
        if (rst) begin
            mem_wb_reg_write <= 0;
            mem_wb_mem_to_reg <= 0;
            mem_wb_read_data <= 0;
            mem_wb_alu_result <= 0;
            mem_wb_rd_addr <= 0;
        end else begin
            mem_wb_reg_write <= ex_mem_reg_write;
            mem_wb_mem_to_reg <= ex_mem_mem_to_reg;
            mem_wb_read_data <= mem_read_data;
            mem_wb_alu_result <= ex_mem_alu_result;
            mem_wb_rd_addr <= ex_mem_rd_addr;
        end
    end

    //================================================================
    // STAGE 5: WRITE BACK (WB)
    //================================================================
    assign wb_write_data = mem_wb_mem_to_reg ? mem_wb_read_data : mem_wb_alu_result;

    // Register File Write Port
    always @(posedge clk) begin
        if (~rst && mem_wb_reg_write && (mem_wb_rd_addr != 0)) begin
            reg_file[mem_wb_rd_addr] <= wb_write_data;
        end
    end

    //================================================================
    // HAZARD DETECTION AND FORWARDING UNIT
    //================================================================

    // Stall logic for load-use hazard
    wire load_use_hazard = (id_ex_mem_read &&
                           ((id_ex_rd_addr == id_rs1_addr && id_rs1_addr != 0) ||
                            (id_ex_rd_addr == id_rs2_addr && id_rs2_addr != 0 && !id_alu_src)));

    assign pc_stall = load_use_hazard;
    assign id_ex_bubble = load_use_hazard || ex_branch_taken;
    assign if_id_flush = ex_branch_taken;

    // Forwarding logic for EX stage
    // Forward from EX/MEM stage (priority 1)
    assign forwardA = (ex_mem_reg_write && (ex_mem_rd_addr != 0) && (ex_mem_rd_addr == id_ex_rs1_addr)) ? 2'b01 :
                      // Forward from MEM/WB stage (priority 2)
                      (mem_wb_reg_write && (mem_wb_rd_addr != 0) && (mem_wb_rd_addr == id_ex_rs1_addr) && !(ex_mem_reg_write && (ex_mem_rd_addr != 0) && (ex_mem_rd_addr == id_ex_rs1_addr))) ? 2'b10 :
                      2'b00; // No forwarding

    assign forwardB = (ex_mem_reg_write && (ex_mem_rd_addr != 0) && (ex_mem_rd_addr == id_ex_rs2_addr) && !id_ex_alu_src) ? 2'b01 :
                      // Forward from MEM/WB stage
                      (mem_wb_reg_write && (mem_wb_rd_addr != 0) && (mem_wb_rd_addr == id_ex_rs2_addr) && !id_ex_alu_src && !(ex_mem_reg_write && (ex_mem_rd_addr != 0) && (ex_mem_rd_addr == id_ex_rs2_addr))) ? 2'b10 :
                      2'b00; // No forwarding

endmodule

examples/generated_chips/generated_risc_8bit_processor/src/risc_8bit_processor_tb.v
/**
 * Testbench for the 8-bit, 5-stage pipelined RISC processor.
 *
 * This testbench performs the following steps:
 * 1. Instantiates the processor DUT.
 * 2. Generates a clock signal.
 * 3. Applies a reset sequence to initialize the processor.
 * 4. Allows the pre-loaded program within the DUT to run to completion.
 * 5. Waits for the processor's 'halted' signal to be asserted.
 * 6. Includes a timeout mechanism to prevent the simulation from running indefinitely.
 * 7. Once halted, it performs self-checking by verifying the final state of
 *    key registers and a specific data memory location against expected values.
 * 8. Prints a clear PASS/FAIL message and terminates the simulation.
 */
 `include "risc_8bit_defines.vh"
module risc_8bit_processor_tb;

    // Include processor definitions. This is necessary for hierarchical access
    // to DUT internal signals and must be placed inside the module.

    // Testbench parameters
    parameter CLK_PERIOD = 10; // Clock period in ns
    parameter TIMEOUT_CYCLES = 200; // Max cycles to wait for halt

    // Testbench signals
    reg clk;
    reg rst;

    // Variable for tracking simulation time. Moved to module scope for Verilog-2001 compatibility.
    integer cycle_counter;

    // Instantiate the Device Under Test (DUT)
    risc_8bit_processor dut (
        .clk(clk),
        .rst(rst)
    );

    // Clock generator
    initial begin
        clk = 1'b0;
        forever #(CLK_PERIOD / 2) clk = ~clk;
    end

    // Main test sequence and self-checking logic
    initial begin
        // Required for waveform generation
        $dumpfile("design.vcd");
        $dumpvars(0, risc_8bit_processor_tb);

        $display("Starting RISC Processor Testbench...");

        // 1. Apply reset
        rst = 1'b1;
        $display("[%0t] Asserting reset.", $time);
        #(2 * CLK_PERIOD);
        rst = 1'b0;
        $display("[%0t] De-asserting reset. Processor running.", $time);

        // 2. Wait for the program to complete (or timeout)
        cycle_counter = 0; // Initialization
        // Use direct hierarchical access to monitor the DUT's halted signal
        while (dut.halted == 1'b0 && cycle_counter < TIMEOUT_CYCLES) begin
            @(posedge clk);
            cycle_counter = cycle_counter + 1;
        end

        // 3. Perform self-checking
        $display("[%0t] Processor halted or timeout reached after %d cycles.", $time, cycle_counter);
        
        // Check for timeout
        if (cycle_counter >= TIMEOUT_CYCLES) begin
            $display("ERROR: Simulation timed out. Processor did not halt.");
            $display("\nSIMULATION FAILED");
            $finish;
        end

        $display("Performing final state checks...");

        // Expected values based on the pre-loaded program
        // R1 = 5
        // R2 = 10
        // R3 = R1 + R2 = 15
        // R4 = 20 (address for SW/LW)
        // data_mem[20] = R3 = 15
        // R5 = data_mem[20] = 15
        // R6 = R2 - R1 = 5
        // BEQ R1, R6 -> branch taken

        // Check Register R1
        if (dut.reg_file[1] !== 8'd5) begin
            $display("ERROR: R1 check failed. Expected: 5, Actual: %d", dut.reg_file[1]);
            $display("\nSIMULATION FAILED");
            $finish;
        end

        // Check Register R2
        if (dut.reg_file[2] !== 8'd10) begin
            $display("ERROR: R2 check failed. Expected: 10, Actual: %d", dut.reg_file[2]);
            $display("\nSIMULATION FAILED");
            $finish;
        end

        // Check Register R3
        if (dut.reg_file[3] !== 8'd15) begin
            $display("ERROR: R3 check failed. Expected: 15, Actual: %d", dut.reg_file[3]);
            $display("\nSIMULATION FAILED");
            $finish;
        end

        // Check Register R4
        if (dut.reg_file[4] !== 8'd20) begin
            $display("ERROR: R4 check failed. Expected: 20, Actual: %d", dut.reg_file[4]);
            $display("\nSIMULATION FAILED");
            $finish;
        end

        // Check Register R5 (result of LW)
        if (dut.reg_file[5] !== 8'd15) begin
            $display("ERROR: R5 check failed. Expected: 15, Actual: %d", dut.reg_file[5]);
            $display("\nSIMULATION FAILED");
            $finish;
        end

        // Check Register R6
        if (dut.reg_file[6] !== 8'd5) begin
            $display("ERROR: R6 check failed. Expected: 5, Actual: %d", dut.reg_file[6]);
            $display("\nSIMULATION FAILED");
            $finish;
        end

        // Check Data Memory (result of SW)
        if (dut.data_mem[20] !== 8'd15) begin
            $display("ERROR: Data Memory[20] check failed. Expected: 15, Actual: %d", dut.data_mem[20]);
            $display("\nSIMULATION FAILED");
            $finish;
        end

        // 4. If all checks pass, print the success message
        $display("All register and memory checks passed.");
        $display("\nSIMULATION PASSED");
        $finish;
    end

endmodule

examples/verilog_designs/generated_risc_8bit/design.vcd
$date
	Thu Aug 28 21:02:25 2025
$end
$version
	Icarus Verilog
$end
$timescale
	1s
$end
$scope module risc_8bit_processor_tb $end
$var parameter 32 ! CLK_PERIOD $end
$var parameter 32 " TIMEOUT_CYCLES $end
$var reg 1 # clk $end
$var reg 1 $ rst $end
$var integer 32 % cycle_counter [31:0] $end
$scope module dut $end
$var wire 1 # clk $end
$var wire 8 & ex_alu_result [7:0] $end
$var wire 1 ' ex_branch_taken $end
$var wire 1 ( id_alu_src $end
$var wire 1 ) id_ex_bubble $end
$var wire 1 * id_reg_write $end
$var wire 1 + if_id_flush $end
$var wire 16 , if_instr [15:0] $end
$var wire 1 - load_use_hazard $end
$var wire 8 . mem_read_data [7:0] $end
$var wire 1 / pc_stall $end
$var wire 1 $ rst $end
$var wire 8 0 wb_write_data [7:0] $end
$var wire 8 1 pc_plus_1 [7:0] $end
$var wire 8 2 pc_next [7:0] $end
$var wire 8 3 id_rs2_data [7:0] $end
$var wire 4 4 id_rs2_addr [3:0] $end
$var wire 8 5 id_rs1_data [7:0] $end
$var wire 4 6 id_rs1_addr [3:0] $end
$var wire 4 7 id_rd_addr [3:0] $end
$var wire 4 8 id_opcode [3:0] $end
$var wire 1 9 id_mem_write $end
$var wire 1 : id_mem_to_reg $end
$var wire 1 ; id_mem_read $end
$var wire 4 < id_imm [3:0] $end
$var wire 1 = id_branch $end
$var wire 3 > id_alu_op [2:0] $end
$var wire 2 ? forwardB [1:0] $end
$var wire 2 @ forwardA [1:0] $end
$var wire 1 A ex_zero_flag $end
$var wire 8 B ex_branch_addr [7:0] $end
$var wire 8 C ex_alu_in2_base [7:0] $end
$var wire 8 D ex_alu_in2 [7:0] $end
$var wire 8 E ex_alu_in1 [7:0] $end
$var parameter 32 F A_WIDTH $end
$var parameter 32 G DMEM_SIZE $end
$var parameter 32 H D_WIDTH $end
$var parameter 32 I IMEM_SIZE $end
$var parameter 4 J OP_ADD $end
$var parameter 4 K OP_ADDI $end
$var parameter 4 L OP_AND $end
$var parameter 4 M OP_BEQ $end
$var parameter 4 N OP_HALT $end
$var parameter 4 O OP_LW $end
$var parameter 4 P OP_NOP $end
$var parameter 4 Q OP_OR $end
$var parameter 4 R OP_SL $end
$var parameter 4 S OP_SUB $end
$var parameter 4 T OP_SW $end
$var parameter 32 U REG_ADDR_WIDTH $end
$var parameter 32 V REG_COUNT $end
$var reg 8 W ex_alu_result_comb [7:0] $end
$var reg 8 X ex_mem_alu_result [7:0] $end
$var reg 1 Y ex_mem_branch_taken $end
$var reg 1 Z ex_mem_mem_read $end
$var reg 1 [ ex_mem_mem_to_reg $end
$var reg 1 \ ex_mem_mem_write $end
$var reg 4 ] ex_mem_rd_addr [3:0] $end
$var reg 1 ^ ex_mem_reg_write $end
$var reg 8 _ ex_mem_store_data [7:0] $end
$var reg 1 ` halted $end
$var reg 3 a id_ex_alu_op [2:0] $end
$var reg 1 b id_ex_alu_src $end
$var reg 1 c id_ex_branch $end
$var reg 4 d id_ex_imm [3:0] $end
$var reg 1 e id_ex_mem_read $end
$var reg 1 f id_ex_mem_to_reg $end
$var reg 1 g id_ex_mem_write $end
$var reg 8 h id_ex_pc_plus_1 [7:0] $end
$var reg 4 i id_ex_rd_addr [3:0] $end
$var reg 1 j id_ex_reg_write $end
$var reg 4 k id_ex_rs1_addr [3:0] $end
$var reg 8 l id_ex_rs1_data [7:0] $end
$var reg 4 m id_ex_rs2_addr [3:0] $end
$var reg 8 n id_ex_rs2_data [7:0] $end
$var reg 16 o if_id_instr [15:0] $end
$var reg 8 p if_id_pc_plus_1 [7:0] $end
$var reg 1 q if_id_valid $end
$var reg 8 r mem_wb_alu_result [7:0] $end
$var reg 1 s mem_wb_mem_to_reg $end
$var reg 4 t mem_wb_rd_addr [3:0] $end
$var reg 8 u mem_wb_read_data [7:0] $end
$var reg 1 v mem_wb_reg_write $end
$var reg 8 w pc [7:0] $end
$var integer 32 x i [31:0] $end
$upscope $end
$upscope $end
$enddefinitions $end
$comment Show the parameter values. $end
$dumpall
b10000 V
b100 U
b11 T
b101 S
b1001 R
b1000 Q
b0 P
b100 O
b1111 N
b110 M
b111 L
b1 K
b10 J
b100000000 I
b1000 H
b100000000 G
b1000 F
b11001000 "
b1010 !
$end
#0
$dumpvars
b10000 x
b0 w
0v
b0 u
b0 t
0s
b0 r
0q
b0 p
b0 o
bx n
bx m
bx l
bx k
0j
b0 i
bx h
0g
0f
0e
bx d
0c
0b
b0 a
0`
b0 _
0^
b0 ]
0\
0[
0Z
0Y
b0 X
b0 W
bx E
bx D
bx C
bx B
xA
b0 @
b0 ?
b0 >
0=
b0 <
0;
0:
09
b0 8
b0 7
b0 6
b0 5
b0 4
b0 3
b1 2
b1 1
b0 0
0/
b0 .
0-
b1000100000101 ,
0+
0*
0)
0(
0'
b0 &
bx %
1$
0#
$end
#5
1#
#10
0#
#15
1#
#20
0#
b0 %
0$
#25
b1 >
1A
b0 D
1*
1(
b0 E
b0 B
b0 C
b1 8
b1 7
b101 4
b101 <
b10 2
bx _
b0 m
b0 k
b0 d
b0 n
b0 l
b0 h
1q
b1 p
b1000100000101 o
b10 1
b1001000001010 ,
b1 w
b1 %
1#
#30
0#
#35
b101 &
b101 W
0A
b101 D
b11 2
b10 7
b1010 4
b1010 <
b101 C
b11 1
b10001100010010 ,
b10 w
b10 p
b1001000001010 o
b1 i
b101 m
b101 d
b110 B
b1 h
1b
b1 a
1j
b0 _
b10 %
1#
#40
0#
#45
b11111010 &
b11111010 W
b11111010 D
1*
0(
b11111010 C
b10 8
b11 7
b1 6
b10 4
b10 <
b100 2
b1 ]
b101 _
b101 X
1^
b10 i
b1010 m
b1010 d
b11111100 B
b10 h
b11 p
b10001100010010 o
b100 1
b1010000001100 ,
b11 w
b11 %
1#
#50
0#
#55
b101 E
b11111111 &
b11111111 W
b10 @
1(
b1 ?
0A
b11111010 D
b101 2
b1 8
b100 7
b0 6
b1100 4
b1100 <
b0 C
b101 0
b101 1
b11001101000000 ,
b100 w
b100 p
b1010000001100 o
b11 i
b10 m
b1 k
b10 d
b101 B
b11 h
0b
b10 ]
b11111010 _
b11111010 X
b1 t
b101 r
1v
b100 %
1#
#60
0#
#65
b0 @
b0 E
0*
b11111100 &
b11111100 W
b0 ?
b11111010 0
b11111100 D
b11111100 C
19
b11 8
b11 7
b100 6
b0 4
b0 <
b110 2
b10 t
b11111010 r
b11 ]
b11111111 X
b100 i
b1100 m
b0 k
b1100 d
b0 B
b100 h
1b
b101 p
b11001101000000 o
b110 1
b100010101000000 ,
b101 w
b101 %
1#
#70
0#
#75
1*
b11111100 &
b11111100 W
b1 >
b11111100 E
b0 D
1(
b1 @
b111 2
1:
1;
09
b100 8
b101 7
b0 C
b11111111 0
b111 1
b101011000100001 ,
b110 w
b110 p
b100010101000000 o
b11 i
b0 m
b100 k
b0 d
b101 B
b101 h
1g
0j
b100 ]
b11111100 _
b11111100 X
b11 t
b11111111 r
b110 %
1#
#80
0#
#85
b11111100 &
b11111100 W
1*
b10 >
0A
b11111100 E
0(
b10 @
b11111010 5
b101 3
b11111100 0
0:
0;
b101 8
b110 7
b10 6
b1 4
b1 <
b1000 2
b100 t
b11111100 r
b11 ]
b0 _
1\
0^
b101 i
b110 B
b110 h
1f
0g
1e
1j
b111 p
b101011000100001 o
b1000 1
b110000101100010 ,
b111 w
b111 %
1#
#90
0#
#95
0*
b11111010 E
b11110101 &
b11110101 W
b0 @
b101 D
b0 5
b11111010 3
b1001 2
1=
b110 8
b1 7
b110 6
b10 4
b10 <
b101 C
b1001 1
b0 ,
b1000 w
b1000 p
b110000101100010 o
b110 i
b1 m
b10 k
b1 d
b101 n
b11111010 l
b1000 B
b111 h
0f
0e
0b
b10 a
b101 ]
1[
0\
1Z
1^
b11 t
0v
b1000 %
1#
#100
0#
#105
b0 >
b11111010 D
b11111011 &
b11111011 W
b1 @
b11110101 E
b0 3
b0 0
b11111010 C
0=
b0 8
b0 7
b0 6
b0 4
b0 <
b1010 2
b101 t
1s
1v
b110 ]
b101 _
b11110101 X
0[
0Z
b1 i
b10 m
b110 k
b10 d
b11111010 n
b0 l
b1010 B
b1000 h
1c
0j
b1001 p
b0 o
b1010 1
b1001 w
b1001 %
1#
#110
0#
#115
1A
b0 D
b0 @
b1011 2
b0 C
b0 &
b0 W
b0 E
b11110101 0
b1011 1
b1111111111111111 ,
b1010 w
b1010 p
b0 i
b0 m
b0 k
b0 d
b0 n
b1001 B
b1001 h
0c
b0 a
b1 ]
b11111010 _
b11111011 X
0^
b110 t
b11110101 r
0s
b1010 %
1#
#120
0#
#125
b11111011 0
b1111 8
b1111 7
b1111 6
b1111 4
b1111 <
b1100 2
b1 t
b11111011 r
0v
b0 ]
b0 _
b0 X
b1010 B
b1010 h
b1011 p
b1111111111111111 o
b1100 1
b0 ,
b1011 w
b1011 %
1#
#130
0#
#135
b1101 2
b0 8
b0 7
b0 6
b0 4
b0 <
b0 0
1`
b1101 1
b1100 w
b1100 p
b0 o
b1111 i
b1111 m
b1111 k
b1111 d
b1010 B
b1011 h
b0 t
b0 r
b1100 %
1#
#140
0#
#145
b1111 ]
b0 i
b0 m
b0 k
b0 d
b1100 B
b1100 h
0q
b1101 p
b1101 %
1#
